[{
  "id": 1,
  "email": "dtolcher0@cmu.edu",
  "password": "rS4}Km3zagX5d"
}, {
  "id": 2,
  "email": "ealleyn1@tumblr.com",
  "password": "fJ7\")TEhYvwF>"
}, {
  "id": 3,
  "email": "dgillibrand2@prweb.com",
  "password": "nT7~B0f?ezI!4"
}, {
  "id": 4,
  "email": "krival3@netscape.com",
  "password": "iI6,+cGtK+mU.6"
}, {
  "id": 5,
  "email": "mabrahmer4@omniture.com",
  "password": "nZ5*VP8}"
}, {
  "id": 6,
  "email": "ckennifick5@dedecms.com",
  "password": "dI1%PXf1UTV9?Oy+"
}, {
  "id": 7,
  "email": "docorr6@nationalgeographic.com",
  "password": "hN9\\oShL#`C"
}]
